dmr/singleton.py
Dmr-0.1.0.dist-info/LICENSE
Dmr-0.1.0.dist-info/METADATA
Dmr-0.1.0.dist-info/WHEEL
Dmr-0.1.0.dist-info/top_level.txt
Dmr-0.1.0.dist-info/RECORD
