Metadata-Version: 2.1
Name: Dmr
Version: 0.1.0
Summary: ESTHDMR utility
Author: Angkana Suchaimanacharoen
Author-email: angkana.suc@eastspring.com
License: LICENSE
License-File: LICENSE
Requires-Dist: pandas
Requires-Dist: numpy
Requires-Dist: pytest
